interactions/ext/get/__init__.py
interactions/ext/get/get.py
interactions/ext/get/get.pyi
interactions_get-1.1.2.dist-info/LICENSE
interactions_get-1.1.2.dist-info/METADATA
interactions_get-1.1.2.dist-info/WHEEL
interactions_get-1.1.2.dist-info/top_level.txt
interactions_get-1.1.2.dist-info/RECORD
