Metadata-Version: 2.1
Name: interactions-get
Version: 1.1.2
Summary: Get method for interactions.py
Home-page: https://github.com/EdVraz/interactions-get
Author: EdVraz
Author-email: edvraz12@gmail.com
License: MIT
Classifier: Programming Language :: Python :: 3
Classifier: Development Status :: 4 - Beta
Classifier: License :: OSI Approved :: MIT License
Classifier: Operating System :: OS Independent
License-File: LICENSE
Requires-Dist: discord-py-interactions (>=4.2.1)
